infi.wmi-0.1.30-py2.7-nspkg.pth
infi/wmi/__init__.py
infi/wmi/__version__.py
infi/wmi/tests.py
infi.wmi-0.1.30.dist-info/LICENSE
infi.wmi-0.1.30.dist-info/METADATA
infi.wmi-0.1.30.dist-info/WHEEL
infi.wmi-0.1.30.dist-info/entry_points.txt
infi.wmi-0.1.30.dist-info/namespace_packages.txt
infi.wmi-0.1.30.dist-info/top_level.txt
infi.wmi-0.1.30.dist-info/RECORD
