Metadata-Version: 2.1
Name: infi.wmi
Version: 0.1.30
Summary: monkeypatched fork of comptypes to support faster WMI access
Home-page: https://github.com/Infinidat/infi.wmi
Author: Arnon Yaari
Author-email: arnony@infinidat.com
License: BSD
Platform: UNKNOWN
Classifier: Intended Audience :: Developers
Classifier: Intended Audience :: System Administrators
Classifier: License :: OSI Approved :: BSD License
Classifier: Operating System :: OS Independent
Classifier: Programming Language :: Python
Classifier: Programming Language :: Python :: 2
Classifier: Programming Language :: Python :: 3
Classifier: Topic :: Software Development :: Libraries :: Python Modules
Requires-Dist: comtypes
Requires-Dist: setuptools
